odimh5/__init__.py
odimh5/reader.py
odimh5-1.0.0.dist-info/LICENSE
odimh5-1.0.0.dist-info/METADATA
odimh5-1.0.0.dist-info/WHEEL
odimh5-1.0.0.dist-info/top_level.txt
odimh5-1.0.0.dist-info/RECORD
