Metadata-Version: 2.1
Name: odimh5
Version: 1.0.0
License-File: LICENSE
Requires-Dist: vptstools
